godot_autobuild/__init__.py
godot_autobuild/__main__.py
godot_autobuild/builder.py
godot_autobuild/cli.py
godot_autobuild/manifest.py
godot_autobuild/godot/__init__.py
godot_autobuild/godot/builder.py
godot_autobuild/godot/local.py
godot_autobuild/godot/version.py
godot_autobuild-0.1.0.dist-info/METADATA
godot_autobuild-0.1.0.dist-info/WHEEL
godot_autobuild-0.1.0.dist-info/entry_points.txt
godot_autobuild-0.1.0.dist-info/licenses/LICENSE
godot_autobuild-0.1.0.dist-info/RECORD
