Metadata-Version: 2.4
Name: godot_autobuild
Version: 0.1.0
Summary: A tool for building godot projects.
Author-email: NoFun <nofuncoding@qq.com>
License-Expression: MIT
License-File: LICENSE
Classifier: Development Status :: 1 - Planning
Classifier: Intended Audience :: Developers
Classifier: License :: OSI Approved :: MIT License
Classifier: Programming Language :: Python :: 3.11
Classifier: Programming Language :: Python :: 3.12
Classifier: Programming Language :: Python :: 3.13
Classifier: Topic :: Software Development :: Build Tools
Requires-Python: >=3.11
Requires-Dist: rich>=14.0.0
Requires-Dist: typer>=0.15.3
